cascade/__init__.py
cascade/agents/__init__.py
cascade/agents/generic.py
cascade/agents/interface.py
cascade/agents/manual.py
cascade/agents/registry.py
cascade/agents/anthropic/__init__.py
cascade/agents/anthropic/claude_api.py
cascade/agents/anthropic/claude_cli.py
cascade/agents/google/__init__.py
cascade/agents/google/gemini_api.py
cascade/agents/google/gemini_cli.py
cascade/agents/openai/__init__.py
cascade/agents/openai/codex_api.py
cascade/agents/openai/codex_cli.py
cascade/cli/__init__.py
cascade/cli/interactive.py
cascade/cli/main.py
cascade/cli/onboarding.py
cascade/cli/styles.py
cascade/cli/themes.py
cascade/cli/ui.py
cascade/cli/commands/__init__.py
cascade/cli/commands/agents.py
cascade/cli/commands/config.py
cascade/cli/commands/destroy.py
cascade/cli/commands/git.py
cascade/cli/commands/init.py
cascade/cli/commands/knowledge.py
cascade/cli/commands/metrics.py
cascade/cli/commands/next.py
cascade/cli/commands/status.py
cascade/cli/commands/ticket.py
cascade/cli/commands/topic.py
cascade/cli/commands/type_cmd.py
cascade/core/__init__.py
cascade/core/context_builder.py
cascade/core/exceptions.py
cascade/core/executor.py
cascade/core/knowledge_base.py
cascade/core/knowledge_extractor.py
cascade/core/metrics.py
cascade/core/planner.py
cascade/core/project.py
cascade/core/prompt_builder.py
cascade/core/quality_gates.py
cascade/core/ticket_manager.py
cascade/core/topic_manager.py
cascade/models/__init__.py
cascade/models/context.py
cascade/models/enums.py
cascade/models/execution.py
cascade/models/knowledge.py
cascade/models/planning.py
cascade/models/project.py
cascade/models/ticket.py
cascade/models/topic.py
cascade/storage/__init__.py
cascade/storage/database.py
cascade/storage/schemas.sql
cascade/utils/__init__.py
cascade/utils/git.py
cascade/utils/logger.py
cascade/utils/tokens.py
cascade_ai-1.0.0.dist-info/METADATA
cascade_ai-1.0.0.dist-info/WHEEL
cascade_ai-1.0.0.dist-info/entry_points.txt
cascade_ai-1.0.0.dist-info/licenses/LICENSE
cascade_ai-1.0.0.dist-info/RECORD
