Metadata-Version: 2.4
Name: cascade-ai
Version: 1.0.0
Summary: Human-Directed AI Development Orchestration System
Project-URL: Homepage, https://github.com/cascade-ai/cascade
Project-URL: Documentation, https://github.com/cascade-ai/cascade#readme
Project-URL: Repository, https://github.com/cascade-ai/cascade
Project-URL: Issues, https://github.com/cascade-ai/cascade/issues
Author: Cascade Contributors
License-Expression: MIT
License-File: LICENSE
Keywords: ai,cli,development,orchestration,project-management,tickets
Classifier: Development Status :: 4 - Beta
Classifier: Environment :: Console
Classifier: Intended Audience :: Developers
Classifier: License :: OSI Approved :: MIT License
Classifier: Operating System :: OS Independent
Classifier: Programming Language :: Python :: 3
Classifier: Programming Language :: Python :: 3.10
Classifier: Programming Language :: Python :: 3.11
Classifier: Programming Language :: Python :: 3.12
Classifier: Topic :: Software Development
Classifier: Topic :: Software Development :: Quality Assurance
Requires-Python: >=3.10
Requires-Dist: click>=8.1.0
Requires-Dist: pydantic>=2.0.0
Requires-Dist: python-dotenv>=1.0.0
Requires-Dist: pyyaml>=6.0
Requires-Dist: questionary>=2.0.0
Requires-Dist: rich>=13.0.0
Requires-Dist: tiktoken
Provides-Extra: dev
Requires-Dist: mypy>=1.0.0; extra == 'dev'
Requires-Dist: pytest-cov>=4.0.0; extra == 'dev'
Requires-Dist: pytest>=7.0.0; extra == 'dev'
Requires-Dist: ruff>=0.1.0; extra == 'dev'
Requires-Dist: types-pyyaml; extra == 'dev'
